CHANGES.md
LICENSE.md
MANIFEST.in
README.md
VERSION
pyproject.toml
requirements-docs.txt
requirements-tests.txt
requirements.txt
setup.py
bin/radical-saga-version
examples/context/context_ssh.py
examples/files/go_file_copy.py
examples/files/go_remotedir_list.py
examples/files/http_file_copy.py
examples/files/sftp_file_copy.py
examples/files/sftp_remotedir_list.py
examples/files/srm_get_size.py
examples/jobs/cobalt.py
examples/jobs/condorjob.py
examples/jobs/loadlevelerjob.py
examples/jobs/localjob.py
examples/jobs/localjobcontainer.py
examples/jobs/lsfjob.py
examples/jobs/pbsgsisshjob.py
examples/jobs/pbsjob.py
examples/jobs/pbsprojob.py
examples/jobs/sgejob.py
examples/jobs/slurmjob.py
examples/jobs/slurmjobcontainer.py
examples/jobs/torque_gsissh_job.py
examples/master_worker/master.py
examples/master_worker/worker.py
examples/misc/inherit_context.py
examples/replica/irods/irods_test.py
examples/resource/amazon_ec2.py
examples/resource/ec2.py
examples/tutorial/saga_example_local.py
examples/tutorial/saga_example_remote.py
examples/tutorial/saga_example_remote_cluster_staging.py
examples/tutorial/saga_example_remote_staging.py
examples/tutorial/mandelbrot/mandelbrot.py
examples/tutorial/mandelbrot/saga_mandelbrot.py
examples/tutorial/mandelbrot/saga_mandelbrot_osg.py
src/radical.saga.egg-info/PKG-INFO
src/radical.saga.egg-info/SOURCES.txt
src/radical.saga.egg-info/dependency_links.txt
src/radical.saga.egg-info/not-zip-safe
src/radical.saga.egg-info/requires.txt
src/radical.saga.egg-info/top_level.txt
src/radical/saga/VERSION
src/radical/saga/__init__.py
src/radical/saga/attributes.py
src/radical/saga/base.py
src/radical/saga/constants.py
src/radical/saga/context.py
src/radical/saga/exceptions.py
src/radical/saga/monitorable.py
src/radical/saga/sasync.py
src/radical/saga/session.py
src/radical/saga/task.py
src/radical/saga/url.py
src/radical/saga/adaptors/__init__.py
src/radical/saga/adaptors/base.py
src/radical/saga/adaptors/aws/__init__.py
src/radical/saga/adaptors/aws/ec2_resource.py
src/radical/saga/adaptors/cobalt/__init__.py
src/radical/saga/adaptors/cobalt/cobaltjob.py
src/radical/saga/adaptors/condor/__init__.py
src/radical/saga/adaptors/condor/condorjob.py
